visionpy/__init__.py
visionpy/abi.py
visionpy/async_contract.py
visionpy/async_vision.py
visionpy/contract.py
visionpy/defaults.py
visionpy/exceptions.py
visionpy/keys/__init__.py
visionpy/keys/encoding.py
visionpy/providers/__init__.py
visionpy/providers/async_http.py
visionpy/providers/http.py
visionpy/version.py
visionpy/vision.py
visionpy-0.0.4.dist-info/LICENSE
visionpy-0.0.4.dist-info/WHEEL
visionpy-0.0.4.dist-info/METADATA
visionpy-0.0.4.dist-info/RECORD
