Metadata-Version: 2.1
Name: visionpy
Version: 0.0.4
Summary: Vision Python client library
Home-page: https://github.com/vision-consensus/vision-python-sdk
License: MIT
Keywords: vision,api,blockchain
Author: mio
Author-email: liurusi.101@gmail.com
Requires-Python: >3.7.1,<4.0
Classifier: Development Status :: 2 - Pre-Alpha
Classifier: Intended Audience :: Developers
Classifier: Intended Audience :: System Administrators
Classifier: License :: OSI Approved :: MIT License
Classifier: Natural Language :: English
Classifier: Programming Language :: Python :: 3
Classifier: Programming Language :: Python :: 3.10
Classifier: Programming Language :: Python :: 3.8
Classifier: Programming Language :: Python :: 3.9
Classifier: Topic :: Software Development :: Libraries :: Python Modules
Requires-Dist: base58 (>=2.0.0,<3.0.0)
Requires-Dist: ecdsa (>=0.15)
Requires-Dist: eth_abi (>=2.1.1,<3.0.0)
Requires-Dist: httpx (>=0.16.1)
Requires-Dist: pycryptodome (>=3.9.7,<4.0.0)
Project-URL: Repository, https://github.com/vision-consensus/vision-python-sdky
